{
 "SoundBanksInfo": {
  "Platform": "Windows",
  "BasePlatform": "Windows",
  "SchemaVersion": "16",
  "SoundBankVersion": "154",
  "SoundBanks": [
   {
    "Id": "3974548175",
    "Type": "Event",
    "GUID": "{25756C56-4838-4FB6-89F8-E250981B9EEB}",
    "Language": "SFX",
    "Hash": "{2D1B2DF9-4371-3C51-1421-3A88B8246830}",
    "ObjectPath": "Play_OBJ_Campfire",
    "ShortName": "Play_OBJ_Campfire",
    "Path": "Event/Play_OBJ_Campfire.bnk",
    "Media": [
     {
      "Id": "40405022",
      "Language": "SFX",
      "Streaming": "false",
      "Location": "Loose",
      "ShortName": "CAMPFIRE\\OBJ_Campfire_Sizzle_07.wav",
      "Path": "Media/40405022.wem",
      "CachePath": "C0/{C000B5F0-5DD9-BFEA-2924-5F851BD0653C}.wem"
     },
     {
      "Id": "90493337",
      "Language": "SFX",
      "Streaming": "false",
      "Location": "Loose",
      "ShortName": "CAMPFIRE\\OBJ_Campfire_Sizzle_01.wav",
      "Path": "Media/90493337.wem",
      "CachePath": "1C/{1C3FCA0F-DEEA-0724-6C7C-C68281358378}.wem"
     },
     {
      "Id": "182979672",
      "Language": "SFX",
      "Streaming": "false",
      "Location": "Loose",
      "ShortName": "CAMPFIRE\\OBJ_Campfire_Sizzle_06.wav",
      "Path": "Media/182979672.wem",
      "CachePath": "4F/{4F7112C5-7D72-7610-E470-B9DE0B929836}.wem"
     },
     {
      "Id": "186240486",
      "Language": "SFX",
      "Streaming": "false",
      "Location": "Loose",
      "ShortName": "CAMPFIRE\\OBJ_Campfire_Crack_05.wav",
      "Path": "Media/186240486.wem",
      "CachePath": "C3/{C3A834A4-727F-E56E-B993-F5D942AFE0D4}.wem"
     },
     {
      "Id": "199980322",
      "Language": "SFX",
      "Streaming": "false",
      "Location": "Loose",
      "ShortName": "CAMPFIRE\\OBJ_Campfire_Crack_06.wav",
      "Path": "Media/199980322.wem",
      "CachePath": "F0/{F04C711A-0B73-91BB-4EA2-F1556D8558F4}.wem"
     },
     {
      "Id": "206417431",
      "Language": "SFX",
      "Streaming": "false",
      "Location": "Loose",
      "ShortName": "CAMPFIRE\\OBJ_Campfire_Sizzle_04.wav",
      "Path": "Media/206417431.wem",
      "CachePath": "C3/{C3955E87-239A-C6C6-5CB1-C36A2077EFB9}.wem"
     },
     {
      "Id": "212846856",
      "Language": "SFX",
      "Streaming": "false",
      "Location": "Loose",
      "ShortName": "CAMPFIRE\\OBJ_Campfire_Crack_03.wav",
      "Path": "Media/212846856.wem",
      "CachePath": "A0/{A04EDBB0-15D8-984F-9601-4CB6D8C7BE1C}.wem"
     },
     {
      "Id": "307454174",
      "Language": "SFX",
      "Streaming": "false",
      "Location": "Loose",
      "ShortName": "CAMPFIRE\\OBJ_Campfire_Crack_07.wav",
      "Path": "Media/307454174.wem",
      "CachePath": "11/{1176D396-93BE-45EF-A969-5ABA246DF5AB}.wem"
     },
     {
      "Id": "405139328",
      "Language": "SFX",
      "Streaming": "false",
      "Location": "Loose",
      "ShortName": "CAMPFIRE\\OBJ_Campfire_Crack_01.wav",
      "Path": "Media/405139328.wem",
      "CachePath": "BE/{BE1DFB89-A5D2-AE14-33CE-AB6534A2D4B9}.wem"
     },
     {
      "Id": "462929836",
      "Language": "SFX",
      "Streaming": "false",
      "Location": "Loose",
      "ShortName": "CAMPFIRE\\OBJ_Campfire_Sizzle_03.wav",
      "Path": "Media/462929836.wem",
      "CachePath": "4B/{4B8A6624-3DCC-4181-C542-08AC2A5DFA6D}.wem"
     },
     {
      "Id": "466546108",
      "Language": "SFX",
      "Streaming": "false",
      "Location": "Loose",
      "ShortName": "CAMPFIRE\\OBJ_Campfire_Sizzle_05.wav",
      "Path": "Media/466546108.wem",
      "CachePath": "98/{9858C932-AEB5-652B-8A67-DBCE5DAB1074}.wem"
     },
     {
      "Id": "503516773",
      "Language": "SFX",
      "Streaming": "false",
      "Location": "Loose",
      "ShortName": "CAMPFIRE\\OBJ_Campfire_Sizzle_02.wav",
      "Path": "Media/503516773.wem",
      "CachePath": "7A/{7A9E9C27-A81F-8C86-05F6-6344E5277974}.wem"
     },
     {
      "Id": "570880879",
      "Language": "SFX",
      "Streaming": "false",
      "Location": "Loose",
      "ShortName": "CAMPFIRE\\OBJ_Campfire_Burn_Loop.wav",
      "Path": "Media/570880879.wem",
      "CachePath": "C1/{C1C8F24C-9591-C34A-CBFA-8550B223A2FE}.wem"
     },
     {
      "Id": "655045986",
      "Language": "SFX",
      "Streaming": "false",
      "Location": "Loose",
      "ShortName": "CAMPFIRE\\OBJ_Campfire_Crack_02.wav",
      "Path": "Media/655045986.wem",
      "CachePath": "AC/{ACA8D0E3-CFF9-924F-1DD8-B145370F9801}.wem"
     },
     {
      "Id": "664806045",
      "Language": "SFX",
      "Streaming": "false",
      "Location": "Loose",
      "ShortName": "CAMPFIRE\\OBJ_Campfire_Crack_04.wav",
      "Path": "Media/664806045.wem",
      "CachePath": "8F/{8F279E8A-E49B-397A-E3F9-DDBAC4879C06}.wem"
     }
    ],
    "Events": [
     {
      "Id": "3974548175",
      "Name": "Play_OBJ_Campfire",
      "ObjectPath": "\\Events\\Default Work Unit\\Play_OBJ_Campfire",
      "GUID": "{25756C56-4838-4FB6-89F8-E250981B9EEB}",
      "DurationType": "Infinite",
      "MediaRefs": [
       {
        "Id": "40405022"
       },
       {
        "Id": "90493337"
       },
       {
        "Id": "182979672"
       },
       {
        "Id": "186240486"
       },
       {
        "Id": "199980322"
       },
       {
        "Id": "206417431"
       },
       {
        "Id": "212846856"
       },
       {
        "Id": "307454174"
       },
       {
        "Id": "405139328"
       },
       {
        "Id": "462929836"
       },
       {
        "Id": "466546108"
       },
       {
        "Id": "503516773"
       },
       {
        "Id": "570880879"
       },
       {
        "Id": "655045986"
       },
       {
        "Id": "664806045"
       }
      ]
     }
    ]
   }
  ],
  "FileHash": "{9EC65F12-CA56-8508-1F54-ED09B4E3B9E8}"
 }
}